README.rst
setup.py
guosen/__init__.py
guosen.egg-info/PKG-INFO
guosen.egg-info/SOURCES.txt
guosen.egg-info/dependency_links.txt
guosen.egg-info/top_level.txt
guosen/data/__init__.py
guosen/data/config.py
guosen/data/core.py
guosen/data/load_benchmark_data.py
guosen/test/__init__.py
guosen/test/test_guosen_data.py
guosen/util/__init__.py
guosen/util/logger.py